translator/__init__.py
translator/shellscript.py
translator/translator.py
translator-0.0.8.dist-info/DESCRIPTION.rst
translator-0.0.8.dist-info/entry_points.txt
translator-0.0.8.dist-info/METADATA
translator-0.0.8.dist-info/metadata.json
translator-0.0.8.dist-info/RECORD
translator-0.0.8.dist-info/top_level.txt
translator-0.0.8.dist-info/WHEEL
